ChaoZhinengTiYjango/README.md
ChaoZhinengTiYjango/__init__.py
ChaoZhinengTiYjango/__main__.py
ChaoZhinengTiYjango/file.epub
ChaoZhinengTiYjango/index.html
ChaoZhinengTiYjango/css/__init__.py
ChaoZhinengTiYjango/css/annotations.css
ChaoZhinengTiYjango/css/main.css
ChaoZhinengTiYjango/css/normalize.css
ChaoZhinengTiYjango/css/popup.css
ChaoZhinengTiYjango/font/__init__.py
ChaoZhinengTiYjango/font/fontello.eot
ChaoZhinengTiYjango/font/fontello.svg
ChaoZhinengTiYjango/font/fontello.ttf
ChaoZhinengTiYjango/font/fontello.woff
ChaoZhinengTiYjango/img/__init__.py
ChaoZhinengTiYjango/img/annotator-glyph-sprite.png
ChaoZhinengTiYjango/img/annotator-icon-sprite.png
ChaoZhinengTiYjango/img/apple-touch-icon.png
ChaoZhinengTiYjango/img/cancelfullscreen.png
ChaoZhinengTiYjango/img/close.png
ChaoZhinengTiYjango/img/fullscreen.png
ChaoZhinengTiYjango/img/loader.gif
ChaoZhinengTiYjango/img/menu-icon.png
ChaoZhinengTiYjango/img/save.png
ChaoZhinengTiYjango/img/saved.png
ChaoZhinengTiYjango/img/settings-s.png
ChaoZhinengTiYjango/img/settings.png
ChaoZhinengTiYjango/img/star.png
ChaoZhinengTiYjango/js/__init__.py
ChaoZhinengTiYjango/js/epub.js
ChaoZhinengTiYjango/js/epub.min.js
ChaoZhinengTiYjango/js/epub.min.map
ChaoZhinengTiYjango/js/hooks.min.js
ChaoZhinengTiYjango/js/hooks.min.map
ChaoZhinengTiYjango/js/reader.js
ChaoZhinengTiYjango/js/reader.js.map
ChaoZhinengTiYjango/js/reader.min.js
ChaoZhinengTiYjango/js/reader.min.map
ChaoZhinengTiYjango/js/hooks/__init__.py
ChaoZhinengTiYjango/js/hooks/extensions/__init__.py
ChaoZhinengTiYjango/js/hooks/extensions/highlight.js
ChaoZhinengTiYjango/js/libs/__init__.py
ChaoZhinengTiYjango/js/libs/jquery.min.js
ChaoZhinengTiYjango/js/libs/localforage.min.js
ChaoZhinengTiYjango/js/libs/screenfull.js
ChaoZhinengTiYjango/js/libs/screenfull.min.js
ChaoZhinengTiYjango/js/libs/zip.min.js
ChaoZhinengTiYjango/js/plugins/__init__.py
ChaoZhinengTiYjango/js/plugins/hypothesis.js
ChaoZhinengTiYjango/js/plugins/search.js
chao_zhineng_ti_yjango-2024.3.4.0.dist-info/METADATA
chao_zhineng_ti_yjango-2024.3.4.0.dist-info/WHEEL
chao_zhineng_ti_yjango-2024.3.4.0.dist-info/entry_points.txt
chao_zhineng_ti_yjango-2024.3.4.0.dist-info/top_level.txt
chao_zhineng_ti_yjango-2024.3.4.0.dist-info/RECORD
